README.rst
setup.py
qduTAportal.egg-info/PKG-INFO
qduTAportal.egg-info/SOURCES.txt
qduTAportal.egg-info/dependency_links.txt
qduTAportal.egg-info/entry_points.txt
qduTAportal.egg-info/not-zip-safe
qduTAportal.egg-info/requires.txt
qduTAportal.egg-info/top_level.txt
src/__init__.py
src/portal.py